README.md
setup.py
torchsnn/__init__.py
torchsnn/stigmergic_module.py
torchsnn.egg-info/PKG-INFO
torchsnn.egg-info/SOURCES.txt
torchsnn.egg-info/dependency_links.txt
torchsnn.egg-info/requires.txt
torchsnn.egg-info/top_level.txt
torchsnn/layers/__init__.py
torchsnn/layers/full_layer.py
torchsnn/layers/simple_layer.py
torchsnn/layers/stigmergic_layer.py
torchsnn/layers/temporal_adapter.py