Metadata-Version: 2.1
Name: torchsnn
Version: 0.1.0
Summary: pytorch implementation of Stigmergic Neural Netowrks
Home-page: https://github.com/galatolofederico/torchsnn
Author: Federico A. Galatolo
Author-email: galatolo.federico@gmail.com
License: UNKNOWN
Platform: UNKNOWN
Classifier: Programming Language :: Python :: 3.6
Classifier: License :: OSI Approved :: GNU General Public License v3 (GPLv3)
Classifier: Operating System :: OS Independent
Classifier: Topic :: Scientific/Engineering :: Artificial Intelligence
Classifier: Intended Audience :: Science/Research
Classifier: Development Status :: 4 - Beta
